{
  "subtitle": "dignissimos ducimus qui", 
  "description": "excepturi sint occaecati cupiditate non provident, similique sunt in culpa qui officia deserunt mollitia animi, id est laborum et dolorum fuga. Et harum quidem rerum facilis est et expedita distinctio. Nam libero tempore, cum soluta nobis est eligendi optio cumque nihil impedit quo minus id quod maxime placeat facere possimus", 
  "language": "eng_GB", 
  "title": "Test article for TYK", 
  "primary_category": "dc60d1bd3f0b4df5ba4d5f78a3cb29e1", 
  "created_at": "2015-06-25T10:32:37.163204+00:00", 
  "featured_in_category": true, 
  "modified_at": "2015-06-25T10:32:37.163414+00:00", 
  "_version": {
    "package_version": "1.2.0", 
    "language_version": "2.7.6", 
    "language": "python", 
    "language_version_string": "2.7.6 (default, Mar 22 2014, 23:03:41) \n[GCC 4.8.2]", 
    "package": "elastic-git"
  }, 
  "linked_pages": [], 
  "id": null, 
  "content": "Sed ut perspiciatis unde omnis iste natus error sit voluptatem accusantium doloremque laudantium, totam rem aperiam, eaque ipsa quae ab illo inventore veritatis et quasi architecto beatae vitae dicta sunt explicabo. Nemo enim ipsam voluptatem quia voluptas sit aspernatur aut odit aut fugit, sed quia consequuntur magni dolores eos qui ratione voluptatem sequi nesciunt. Neque porro quisquam est, qui dolorem ipsum quia dolor sit amet, consectetur, adipisci velit, sed quia non numquam eius modi tempora incidunt ut labore et dolore magnam aliquam quaerat voluptatem. Ut enim ad minima veniam, quis nostrum exercitationem ullam corporis suscipit laboriosam, nisi ut aliquid ex ea commodi consequatur? Quis autem vel eum iure reprehenderit qui in ea voluptate velit esse quam nihil molestiae consequatur, vel illum qui dolorem eum fugiat quo voluptas nulla pariatur?", 
  "source": null, 
  "featured": false, 
  "author_tags": [], 
  "image": null, 
  "published": null, 
  "position": 0, 
  "image_host": "http://qa.thumbor.unicore.io", 
  "slug": "test-article-tyk", 
  "uuid": "f20e8b0014e84805a026615f1c5a0c17"
}